FuncNotify/EmailMethod.py
FuncNotify/NotifyDecorators.py
FuncNotify/NotifyMethods.py
FuncNotify/PrintMethod.py
FuncNotify/SlackMethod.py
FuncNotify/TeamsMethod.py
FuncNotify/TextMethod.py
FuncNotify/_TemplateMethod_.py
FuncNotify/__init__.py
FuncNotify/__main__.py
tests/__init__.py
tests/test_abstract.py
tests/test_emailtwilio.py
tests/test_emailyag.py
tests/test_print.py
tests/test_slack.py
tests/test_teams.py
tests/test_text.py
FuncNotify-1.3.7.dist-info/LICENSE
FuncNotify-1.3.7.dist-info/METADATA
FuncNotify-1.3.7.dist-info/WHEEL
FuncNotify-1.3.7.dist-info/entry_points.txt
FuncNotify-1.3.7.dist-info/top_level.txt
FuncNotify-1.3.7.dist-info/RECORD
