Metadata-Version: 2.1
Name: FuncNotify
Version: 1.3.7
Summary: Get notified when your functions finish running
Home-page: https://github.com/kevinfjiang/FuncNotify
Author: kevinfjiang
Author-email: kevin.jiang016@gmail.com
License: MIT
Platform: UNKNOWN
Classifier: Intended Audience :: Developers
Classifier: Intended Audience :: Science/Research
Classifier: License :: OSI Approved :: MIT License
Classifier: Programming Language :: Python :: 3
License-File: LICENSE
Requires-Dist: python-dotenv
Requires-Dist: requests
Requires-Dist: slackclient
Requires-Dist: twilio
Requires-Dist: yagmail
Requires-Dist: keyring
Requires-Dist: sendgrid
